Metadata-Version: 1.1
Name: forwardref-inspect
Version: 0.1.0
Summary: Python utility to cope with string-typed type annotations.
Home-page: https://github.com/frankie567/forwardref_inspect
Author: François Voron
Author-email: fvoron@gmail.com
License: MIT
Platform: UNKNOWN
Classifier: Development Status :: 2 - Pre-Alpha
Classifier: Programming Language :: Python
Classifier: Programming Language :: Python :: 2
Classifier: Programming Language :: Python :: 2.7
Classifier: Programming Language :: Python :: 3
Classifier: Programming Language :: Python :: 3.4
Classifier: Programming Language :: Python :: 3.5
